README.md
setup.py
hetpy/__init__.py
hetpy.egg-info/PKG-INFO
hetpy.egg-info/SOURCES.txt
hetpy.egg-info/dependency_links.txt
hetpy.egg-info/requires.txt
hetpy.egg-info/top_level.txt
hetpy/enums/__init__.py
hetpy/enums/projectionEnums.py
hetpy/exceptions/commonExceptions.py
hetpy/exceptions/typeExceptions.py
hetpy/graphUtils/__init__.py
hetpy/graphUtils/graphCreationUtils.py
hetpy/graphUtils/metaProjections.py
hetpy/models/__init__.py
hetpy/models/edge.py
hetpy/models/hetGraph.py
hetpy/models/hetPaths.py
hetpy/models/metaPath.py
hetpy/models/node.py
hetpy/utils/__init__.py
hetpy/utils/utils.py
tests/test_classes.py
tests/test_graphFileExport.py
tests/test_graphMetric.py
tests/test_graphUtils.py
tests/test_igraphWrapping.py
tests/test_metaPaths.py