Metadata-Version: 2.1
Name: hetpy
Version: 1.0.2
Summary: A package to handle heterogeneous information networks
Home-page: https://github.com/codingfabi/hetpy
Author: Fabian Kneissl
Author-email: fabian.kneissl@gmx.de
License: GNU General Public License
